MANIFEST.in
README.rst
gpl.txt
setup.py
src/quaternion/__init__.py
src/quaternion/quaternion.c
src/quaternion/quaternion.h
src/quaternion/quaternion.py
src/quaternion_algebra.egg-info/PKG-INFO
src/quaternion_algebra.egg-info/SOURCES.txt
src/quaternion_algebra.egg-info/dependency_links.txt
src/quaternion_algebra.egg-info/top_level.txt