Metadata-Version: 1.0
Name: quaternion-algebra
Version: 1.0.1
Summary: Quaternion algebra for Python.
Home-page: https://bitbucket.org/sirex/quaternion
Author: UNKNOWN
Author-email: UNKNOWN
License: GPL
Platform: UNKNOWN
